{"completed_in": 0.108, "max_id": 1373445378117267459, "max_id_str": "1373445378117267459", "next_results": "?max_id=1373056658079813632&q=%28online%20school%29%20AND%20%28online%20learning%29%20-filter%3Aretweets&lang=en&count=100&include_entities=1", "query": "%28online+school%29+AND+%28online+learning%29+-filter%3Aretweets", "refresh_url": "?since_id=1373445378117267459&q=%28online%20school%29%20AND%20%28online%20learning%29%20-filter%3Aretweets&lang=en&include_entities=1", "count": 100, "since_id": 0, "since_id_str": "0"}